{"cameraMode":{"drawMode":0,"name":"Shaded","section":"Shading Mode"},"sceneLighting":true,"audioPlay":false,"sceneViewState":{"showFog":true,"showMaterialUpdate":false,"showSkybox":true,"showFlares":true,"showImageEffects":true,"showParticleSystems":true},"in2DMode":false,"pivot":{"x":-42.62111282348633,"y":31.151369094848634,"z":6.656216621398926},"rotation":{"x":0.025532525032758714,"y":-0.6719644665718079,"z":0.023192010819911958,"w":0.7397802472114563},"size":78.75664520263672,"orthographic":false}